my_django_seed
