Metadata-Version: 1.1
Name: my-django-seed
Version: 1.1.8
Summary: Seed your Django project with fake data, this is a fork of the original django_seed to support 2.7 with small changes.
Home-page: UNKNOWN
Author: Moti shakuri
Author-email: motishaku@gmail.com
License: MIT
Keywords: faker fixtures data test django seed
Platform: UNKNOWN
Classifier: Development Status :: 3 - Alpha
Classifier: Intended Audience :: Information Technology
Classifier: License :: OSI Approved :: MIT License
Classifier: Framework :: Django
Classifier: Framework :: Django :: 1.7
Classifier: Framework :: Django :: 1.8
Classifier: Natural Language :: English
Classifier: Programming Language :: Python
Classifier: Programming Language :: Python :: 2
Classifier: Programming Language :: Python :: 2.7
Classifier: Programming Language :: Python :: 3
Classifier: Programming Language :: Python :: 3.2
Classifier: Programming Language :: Python :: 3.4
Classifier: Programming Language :: Python :: 3.5
Classifier: Topic :: Software Development :: Libraries :: Python Modules
Classifier: Topic :: Software Development :: Testing
Classifier: Topic :: Utilities
